streamlitrunner/__init__.py
streamlitrunner/streamlitrunner.py
streamlitrunner/streamlitrunner.pyi
streamlitrunner-0.1.1.dist-info/METADATA
streamlitrunner-0.1.1.dist-info/WHEEL
streamlitrunner-0.1.1.dist-info/licenses/LICENSE.txt
streamlitrunner-0.1.1.dist-info/RECORD
