Metadata-Version: 2.4
Name: streamlitrunner
Version: 0.1.1
Summary: A module to run streamlit apps as local apps
Project-URL: Documentation, https://streamlitrunner.readthedocs.io/en/latest/
Project-URL: Issues, https://github.com/diogo-rossi/streamlitrunner/issues
Project-URL: Source, https://github.com/diogo-rossi/streamlitrunner
Author-email: Diogo Rossi <rossi.diogo@gmail.com>
License-File: LICENSE.txt
Classifier: Programming Language :: Python :: 3.10
Classifier: Programming Language :: Python :: Implementation :: CPython
Classifier: Programming Language :: Python :: Implementation :: PyPy
Requires-Python: >=3.10
Requires-Dist: pywebview>=6.1
Requires-Dist: streamlit>=1.52.2
